csvtoparquet-lib/__init__.py
csvtoparquet-lib/connect.py
csvtoparquet-lib/convert_module.py
csvtoparquet-lib/helpers.py
csvtoparquet-lib/object_module.py
csvtoparquetlib/__init__.py
csvtoparquetlib/connect.py
csvtoparquetlib/convert_module.py
csvtoparquetlib/helpers.py
csvtoparquetlib/object_module.py
csvtoparquetlib-0.1.4.dist-info/METADATA
csvtoparquetlib-0.1.4.dist-info/RECORD
csvtoparquetlib-0.1.4.dist-info/WHEEL
csvtoparquetlib-0.1.4.dist-info/top_level.txt
